{
  "documentBinary": "9743yfshibfkjnjkjklfdjbgsuog==",
  "documentMetadata": {
    "classIndex": {
      "ef": {
        "dTRN": "9443402451823",
        "locationCode": "731",
        "category": "a-Category1",
        "enquiryReference": "UYp3V0",
        "caseReference": "ABC01234"
      }
    },
    "docType": "VoHl",
    "docDate": "2000-02-29",
    "docBinaryHash": "c186S8wUObpPHoQ6Y/0s+g==",
    "docBinaryRef": "qVX29XN0iireH",
    "docBinaryType": "doc",
    "creatingUser": "YIfD",
    "docDescription": "fS6k2abFoTNuirZSLQw7",
    "docPages": 51255414,
    "allocateToUser": "*AUTO*"
  }
}
